{"cameraMode":{"drawMode":0,"name":"Shaded","section":"Shading Mode"},"sceneLighting":false,"audioPlay":false,"sceneViewState":{"showFog":true,"showMaterialUpdate":false,"showSkybox":false,"showFlares":true,"showImageEffects":true,"showParticleSystems":true},"in2DMode":false,"pivot":{"x":-0.283003568649292,"y":-112.5968246459961,"z":62.661903381347659},"rotation":{"x":0.5092234015464783,"y":-0.010334422811865807,"z":0.006092965602874756,"w":0.8605794906616211},"size":137.42977905273438,"orthographic":false}